{"stats":{"minecraft:crafted":{"minecraft:oak_planks":32,"minecraft:crafting_table":1,"minecraft:stick":8},"minecraft:picked_up":{"minecraft:feather":2,"minecraft:chicken":3,"minecraft:wheat_seeds":3,"minecraft:porkchop":2,"minecraft:oak_log":8,"minecraft:bread":6,"byg:cattail":1,"minecraft:mutton":3,"minecraft:white_wool":3},"minecraft:mined":{"minecraft:grass":27,"minecraft:oak_log":8,"byg:short_grass":2,"byg:cattail":2},"minecraft:killed_by":{"mowziesmobs:foliaath":1},"minecraft:used":{"minecraft:wooden_sword":44,"minecraft:bread":3},"minecraft:custom":{"minecraft:time_since_rest":4226,"minecraft:play_one_minute":12202,"minecraft:crouch_one_cm":350,"minecraft:deaths":1,"minecraft:sprint_one_cm":40370,"minecraft:damage_taken":120,"minecraft:walk_one_cm":25293,"minecraft:sneak_time":149,"minecraft:walk_under_water_one_cm":1650,"minecraft:mob_kills":7,"minecraft:drop":1,"minecraft:jump":262,"minecraft:damage_dealt":597,"minecraft:walk_on_water_one_cm":3057,"minecraft:time_since_death":4191,"minecraft:swim_one_cm":16070,"minecraft:fall_one_cm":3460,"minecraft:fly_one_cm":45267},"minecraft:killed":{"minecraft:sheep":3,"minecraft:pig":1,"minecraft:chicken":3},"minecraft:dropped":{"minecraft:chicken":1}},"DataVersion":2586}